siba/__init__.py
siba/siba/__init__.py
siba/siba/progress_bar.py
siba-1.0.5.dist-info/METADATA
siba-1.0.5.dist-info/WHEEL
siba-1.0.5.dist-info/top_level.txt
siba-1.0.5.dist-info/RECORD
