Metadata-Version: 2.1
Name: siba
Version: 1.0.5
Summary: A toolkits for replacing tqdm without additional package install!
Author: dochi
Keywords: siba,i_cant_use_tqdm
Classifier: Programming Language :: Python :: 3
Classifier: Development Status :: 4 - Beta
Requires-Python: >=3
